[
    {
        "accuracy": 0.8731,
        "batch": 8,
        "dropout": 0.025693364190435997,
        "duration": 7660861481850,
        "lr": 0.06328178949979993,
        "momentum": 0.1490443476695409,
        "transform": "echo_256",
        "uid": "c417e405de5be38c275670bc58ee557c"
    },
    {
        "accuracy": 0.8604,
        "batch": 32,
        "dropout": 0.33992775282064114,
        "duration": 3317565804666,
        "lr": 0.3036417374163531,
        "momentum": 0.346632548183453,
        "transform": "norm_128_flip",
        "uid": "d1e3bf2fbd10a84eb797f0caac469b3b"
    },
    {
        "accuracy": 0.5949,
        "batch": 32,
        "dropout": 0.41758108313613945,
        "duration": 1292872412214,
        "lr": 3.4345791725938096e-05,
        "momentum": 0.9723696796018774,
        "transform": "echo_64_flip",
        "uid": "d82f937d96e9841b75381e712ce1cfde"
    },
    {
        "accuracy": 0.5328,
        "batch": 32,
        "dropout": 0.42397941510041376,
        "duration": 9657943341753,
        "lr": 0.0019680999410440258,
        "momentum": 0.15460122365626194,
        "transform": "echo_256_flip",
        "uid": "a0a8067c96c8ff2970aabe225988700c"
    }
]