[
    {
        "accuracy": 0.5220026969909668,
        "batch": 64,
        "duration": 24424197123593,
        "lr": 0.00045991212043423364,
        "momentum": 0.8427708402325392,
        "transform": "echo_256",
        "uid": "12356fdba813bbea9ed81da8039ff51b"
    },
    {
        "accuracy": 0.43864139914512634,
        "batch": 32,
        "duration": 22551752895092,
        "lr": 0.008059774808305588,
        "momentum": 0.6303103147686214,
        "transform": "echo_128_flip",
        "uid": "86bd68761e0268c36aff3b409b3ee167"
    },
    {
        "accuracy": 0.4301133155822754,
        "batch": 32,
        "duration": 22021026562003,
        "lr": 0.01842412179854618,
        "momentum": 0.9049366065729001,
        "transform": "echo_64_flip",
        "uid": "924c3f29ea6fd3eed3338ce4b2e2fbd8"
    },
    {
        "accuracy": 0.36917904019355774,
        "batch": 64,
        "duration": 21694992314819,
        "lr": 0.08320128595382785,
        "momentum": 0.8365908585020803,
        "transform": "echo_32_flip",
        "uid": "d6893abd119b9be6ed5a5104e4c42a33"
    },
    {
        "accuracy": 0.3256433308124542,
        "batch": 8,
        "duration": 22113277039804,
        "lr": 2.9822398902292085e-05,
        "momentum": 0.12187171039663924,
        "transform": "echo_64",
        "uid": "1bf2acb1a46431427ddd64d02b9a9d3d"
    },
    {
        "accuracy": 0.28909024596214294,
        "batch": 16,
        "duration": 57587553335777,
        "lr": 0.00017721931303073284,
        "momentum": 0.20827408013428916,
        "transform": "echo_32",
        "uid": "679eb612c59930266ce363de8af6c18e"
    }
]