[
    {
        "accuracy": 0.9928,
        "batch": 2,
        "duration": 5764949182950,
        "lr": 0.12342851965547155,
        "momentum": 0.4903587317255893,
        "transform": "norm_32",
        "uid": "729c1fa9a28d3dbc65cbd8d5300bcf4e"
    },
    {
        "accuracy": 0.9903,
        "batch": 2,
        "duration": 5760247108723,
        "lr": 0.02902790252170875,
        "momentum": 0.7325153794835008,
        "transform": "norm_32_flip",
        "uid": "ced690c447e470bb381f23213d6003fa"
    },
    {
        "accuracy": 0.9903,
        "batch": 8,
        "duration": 3615548589531,
        "lr": 0.0031525371566376455,
        "momentum": 0.19519138344382614,
        "transform": "norm_32",
        "uid": "0a42cf7864ab7399606742ff84ac5aaf"
    },
    {
        "accuracy": 0.9902,
        "batch": 32,
        "duration": 1676751866648,
        "lr": 0.0010920247773152129,
        "momentum": 0.7592234708726827,
        "transform": "norm_32",
        "uid": "d40fc768dee9679eb53279906045cb3b"
    },
    {
        "accuracy": 0.9883,
        "batch": 8,
        "duration": 3646441720978,
        "lr": 0.00724635190873163,
        "momentum": 0.6025343742922522,
        "transform": "echo_32_flip",
        "uid": "f19cfd2fbbc5bcbde99b781698a0f487"
    },
    {
        "accuracy": 0.9845,
        "batch": 128,
        "duration": 1460336784850,
        "lr": 0.01814583471183242,
        "momentum": 0.029873278115058466,
        "transform": "norm_32_flip",
        "uid": "c5899293b953f69ff5ae699ed158d6f3"
    }
]