[
    {
        "accuracy": 0.7573,
        "batch": 256,
        "duration": 1168854055572,
        "lr": 0.3152328780527112,
        "momentum": 0.8607424643534282,
        "transform": "norm_64_flip",
        "uid": "aa59513f5ea1926eb6c8c405dacc0e4c"
    },
    {
        "accuracy": 0.5511,
        "batch": 256,
        "duration": 1358843012003,
        "lr": 0.3504016343146241,
        "momentum": 0.425976149761363,
        "transform": "norm_256",
        "uid": "1bc7619a0d05c4812813ff727b07baee"
    },
    {
        "accuracy": 0.4902,
        "batch": 2048,
        "duration": 171952944330,
        "lr": 0.0011970937170628323,
        "momentum": 0.90574907152883,
        "transform": "norm_64_flip",
        "uid": "5a89728c786b6fd3f59b3b60c080805f"
    },
    {
        "accuracy": 0.3955,
        "batch": 8,
        "duration": 2014027799045,
        "lr": 5.8306040875591195e-05,
        "momentum": 0.22803333437013185,
        "transform": "echo_128",
        "uid": "7d324ce8c929a0ceea386ed8e4026f76"
    }
]