[
    {
        "accuracy": 0.9807,
        "batch": 64,
        "duration": 77267467334,
        "lr": 0.010063145372137712,
        "momentum": 0.07710725585190237,
        "transform": "norm",
        "uid": "27de4f4b6bee2713c4a4c46ef02134a2"
    },
    {
        "accuracy": 0.8568,
        "batch": 4,
        "duration": 4880369469713,
        "lr": 0.4992827167270129,
        "momentum": 0.5808489414760072,
        "transform": "echo_299",
        "uid": "d8f8491dae1272929e830c709ae2d85f"
    },
    {
        "accuracy": 0.8037,
        "batch": 8,
        "duration": 373799022580,
        "lr": 4.4939599522991274e-05,
        "momentum": 0.6183420713568277,
        "transform": "echo_32_flip",
        "uid": "1b9aa0d1b3c8bf1de06244cda9806b42"
    }
]