[
    {
        "accuracy": 0.4978,
        "batch": 64,
        "dropout": 0.3546066359896889,
        "duration": 1511704507098,
        "lr": 0.10950135125122042,
        "momentum": 0.5241328128610728,
        "transform": "norm_299",
        "uid": "6c3fafc232642b264da92dd22e5b583f"
    },
    {
        "accuracy": 0.4059,
        "batch": 4,
        "dropout": 0.311554517604951,
        "duration": 1410130226082,
        "lr": 0.0013096761200837416,
        "momentum": 0.8377330809074792,
        "transform": "echo_256",
        "uid": "8ea85a0afbf3cbd49bc73b37ff117efc"
    }
]