[
    {
        "accuracy": 0.8072,
        "batch": 128,
        "duration": 60732732773,
        "lr": 0.22281633488992622,
        "momentum": 0.6524748330865693,
        "transform": "echo",
        "uid": "1cc982121c9349170a547af75a603cb3"
    },
    {
        "accuracy": 0.755,
        "batch": 256,
        "duration": 667393242419,
        "lr": 0.00993904336256402,
        "momentum": 0.322366564801722,
        "transform": "norm_128_flip",
        "uid": "89806ee5a6ff4e63a8df8eb820c2698c"
    },
    {
        "accuracy": 0.6933,
        "batch": 2048,
        "duration": 90111524527,
        "lr": 0.06276040074308879,
        "momentum": 0.7478815086222148,
        "transform": "norm_32",
        "uid": "df04903727caaee081a42603d8690e30"
    },
    {
        "accuracy": 0.6479,
        "batch": 64,
        "duration": 106004267075,
        "lr": 0.005129522952067677,
        "momentum": 0.24203947219518462,
        "transform": "norm_32",
        "uid": "3281e108279a9fadcb6b20d00a61ebd9"
    },
    {
        "accuracy": 0.5685,
        "batch": 64,
        "duration": 7535092037825,
        "lr": 0.000902490168322877,
        "momentum": 0.4374936087337805,
        "transform": "norm_299",
        "uid": "2f4d3a053978a5cea9f443354811951e"
    },
    {
        "accuracy": 0.5427,
        "batch": 2048,
        "duration": 56899230920,
        "lr": 0.003076823770595887,
        "momentum": 0.012349634980593271,
        "transform": "echo",
        "uid": "8cc045d172a8209e1b8f58de47c44f29"
    },
    {
        "accuracy": 0.3942,
        "batch": 8,
        "duration": 628561440301,
        "lr": 1.0530564333562261e-05,
        "momentum": 0.5891811893449823,
        "transform": "norm_32",
        "uid": "ad4f012f87150233c1dbed47a8ab55bc"
    }
]