[
    {
        "accuracy": 0.6611,
        "batch": 4,
        "dropout": 0.168508621534403,
        "duration": 250906423370,
        "lr": 0.005856066705597091,
        "momentum": 0.4370225153555226,
        "transform": "norm_128",
        "uid": "7229b5b141a9998966ae28666dc95b8b"
    },
    {
        "accuracy": 0.6207,
        "batch": 128,
        "dropout": 0.6,
        "lr": 0.01,
        "momentum": 0.95,
        "transform": "norm_256_flip",
        "uid": "6a9706d459960d485af6f3d6b77501f4"
    },
    {
        "accuracy": 0.4884,
        "batch": 128,
        "dropout": 0.44894841484422354,
        "duration": 14815186697,
        "lr": 0.04436595033656805,
        "momentum": 0.6807649450566485,
        "transform": "echo_flip",
        "uid": "f0dc22de11adb3702a61ab29c33addad"
    }
]