[
    {
        "accuracy": 0.9939,
        "batch": 16,
        "dropout": 0.01096174253143567,
        "duration": 2111424373748,
        "lr": 0.10075469661897321,
        "momentum": 0.5972021402579581,
        "transform": "echo_64",
        "uid": "c8f5d01f548a325f4d1921600ebacf8b"
    },
    {
        "accuracy": 0.988,
        "batch": 4,
        "dropout": 0.39530411537730115,
        "duration": 3796311964713,
        "lr": 0.44599484929363625,
        "momentum": 0.18756041762193254,
        "transform": "norm_299_flip",
        "uid": "a87888f3bf04596b1d25bd9c2363b3f6"
    }
]