[
    {
        "accuracy": 0.16743940114974976,
        "batch": 16,
        "dropout": 0.24724092703547673,
        "duration": 35430486905125,
        "lr": 2.8541109074824788e-05,
        "momentum": 0.6702040488409923,
        "transform": "echo_256_flip",
        "uid": "63649a0ed98d829bf583febfeb07ad43"
    },
    {
        "accuracy": 0.13529065251350403,
        "batch": 512,
        "dropout": 0.4032625795516102,
        "duration": 5038720824377,
        "lr": 3.299210939957205e-05,
        "momentum": 0.6909728801354293,
        "transform": "echo_32_flip",
        "uid": "a41eda519b4109dd5d64182b3b4f6ac9"
    }
]