[
    {
        "accuracy": 0.7801273885350318,
        "batch": 64,
        "dropout": 0.32782495532732514,
        "duration": 7155167870951,
        "lr": 0.20585721820428962,
        "momentum": 0.04917576781430566,
        "transform": "norm_299_flip",
        "uid": "49e000ba0f974328cb475560af653ba0"
    },
    {
        "accuracy": 0.7694267515923567,
        "batch": 2,
        "dropout": 0.07568115914437112,
        "duration": 2497444425750,
        "lr": 0.02384182835607594,
        "momentum": 0.6810446700874725,
        "transform": "norm_256",
        "uid": "636528cdd0c6b30ac1f7ec6041244b34"
    },
    {
        "accuracy": 0.6919745222929936,
        "batch": 8,
        "dropout": 0.01821075383730636,
        "duration": 685404416115,
        "lr": 0.40129360508984696,
        "momentum": 0.006236483477023547,
        "transform": "norm_128_flip",
        "uid": "1d40e0f9a1692eac2bfdf2ca44958bec"
    },
    {
        "accuracy": 0.3648407643312102,
        "batch": 16,
        "dropout": 0.037900449512628276,
        "duration": 786729780358,
        "lr": 0.0021174857229790353,
        "momentum": 0.6527875782853685,
        "transform": "echo_299_flip",
        "uid": "f4870ea07768af2e3eaec17304c297d6"
    },
    {
        "accuracy": 0.21146496815286625,
        "batch": 32,
        "dropout": 0.11745492581997746,
        "duration": 593605306912,
        "lr": 0.0012586827925801345,
        "momentum": 0.266514568172191,
        "transform": "echo_256",
        "uid": "c9f2bb0deddeab40b464668a65566115"
    }
]