[
    {
        "accuracy": 0.7095,
        "batch": 64,
        "duration": 239287951221,
        "lr": 0.00092243071436156,
        "momentum": 0.9751321679160172,
        "transform": "echo_64",
        "uid": "1d1b80345472182c9b3022ae19d8f53c"
    },
    {
        "accuracy": 0.4672,
        "batch": 64,
        "duration": 10402327759762,
        "lr": 0.039970217571346944,
        "momentum": 0.6116861689862644,
        "transform": "norm_299",
        "uid": "c4edc01c742879b61d32a8f662e4f3bb"
    }
]