[
    {
        "accuracy": 0.2617,
        "batch": 4,
        "duration": 1503586215005,
        "lr": 0.002553334831698569,
        "momentum": 0.8657199710556915,
        "random_beta": 0.06679286876991719,
        "random_rho_initial": 0.21440000217184263,
        "random_sigma": 0.3617092777804811,
        "transform": "norm_32",
        "uid": "aca2609f7b63708f17dabb0087202faf"
    },
    {
        "accuracy": 0.2356,
        "batch": 128,
        "duration": 584079269321,
        "lr": 0.22553094439783977,
        "momentum": 0.33753342761464766,
        "random_beta": 0.6209016591499892,
        "random_rho_initial": 0.5698404180822906,
        "random_sigma": 0.221744031319155,
        "transform": "echo_32",
        "uid": "8765ec37890c63ad8cfbc1653337ff39"
    }
]