[
    {
        "accuracy": 0.9924,
        "batch": 64,
        "duration": 1136912451145,
        "lr": 0.5483371619178435,
        "momentum": 0.6355766508757041,
        "transform": "norm_128_flip",
        "uid": "7c186e3ce2f4430a190b785533a9ca10"
    },
    {
        "accuracy": 0.5552,
        "batch": 8,
        "duration": 2432973573758,
        "lr": 0.000261099084237336,
        "momentum": 0.27203550073970706,
        "transform": "norm_256",
        "uid": "79f6023e26068eef2bd075d98259b37e"
    }
]