[
    {
        "accuracy": 0.993,
        "batch": 64,
        "duration": 1980785176277,
        "lr": 0.5483371619178435,
        "momentum": 0.6355766508757041,
        "transform": "norm_128_flip",
        "uid": "0c8937d495c03404bdc0dc38056a89cc"
    },
    {
        "accuracy": 0.6546,
        "batch": 8,
        "duration": 4315767359412,
        "lr": 0.000261099084237336,
        "momentum": 0.27203550073970706,
        "transform": "norm_256",
        "uid": "79f6023e26068eef2bd075d98259b37e"
    }
]