[
    {
        "accuracy": 0.396687898089172,
        "batch": 2,
        "duration": 291909592313,
        "kernel_size": 0.12026914691782287,
        "lr": 0.025035077474413952,
        "momentum": 0.6064736816150402,
        "transform": "echo_32",
        "uid": "ceb6471bb1045fadb5d253ed13fcbe3a"
    },
    {
        "accuracy": 0.39261146496815286,
        "batch": 1,
        "duration": 379759159000,
        "kernel_size": 0.10417593931237012,
        "lr": 0.028980256176273696,
        "momentum": 0.07830659190324352,
        "transform": "norm_32",
        "uid": "d661ff34d988b09beea6a9208b18f309"
    }
]