[
    {
        "accuracy": 0.9376152427781193,
        "batch": 64,
        "dropout": 0.09384423019251337,
        "duration": 404472667615,
        "lr": 0.003813539787214301,
        "momentum": 0.8577166912280886,
        "transform": "echo_64",
        "uid": "a53eb8e988012ff32cd53f7f0b032d76"
    },
    {
        "accuracy": 0.4584741856177013,
        "batch": 1024,
        "dropout": 0.18018412109637327,
        "duration": 375905805397,
        "lr": 0.05669068563519247,
        "momentum": 0.587290133453391,
        "transform": "norm_64_flip",
        "uid": "842a2d6d79c4144d76eef3f4231f9f6f"
    },
    {
        "accuracy": 0.19591272280270436,
        "batch": 256,
        "dropout": 0.17144515640091534,
        "duration": 1674980566792,
        "lr": 7.342841045033071e-05,
        "momentum": 0.7097857879111922,
        "transform": "norm_128_flip",
        "uid": "a8e83bebfc6592ab3d4929f38dc1e2e9"
    }
]