[
    {
        "accuracy": 0.8847188076213891,
        "batch": 32,
        "dropout": 0.3707605646304257,
        "duration": 517054345710,
        "lr": 0.025220498833291503,
        "momentum": 0.5974711234145393,
        "transform": "norm_flip",
        "uid": "d0444ac9e6ab83e8ecf3e1d4a353b959"
    },
    {
        "accuracy": 0.211240012292563,
        "batch": 64,
        "dropout": 0.30082236260899436,
        "duration": 1550211992516,
        "lr": 7.465795173349053e-05,
        "momentum": 0.9079746015531155,
        "transform": "norm_128",
        "uid": "ad64c5ff7b4f1a1df4b2063b4775b034"
    },
    {
        "accuracy": 0.19579748002458514,
        "batch": 64,
        "dropout": 0.06500745792846535,
        "duration": 591295576954,
        "lr": 2.667276256278498e-05,
        "momentum": 0.8124404443360184,
        "transform": "echo_128_flip",
        "uid": "a0eae69f590bd2ff3cb9e120a41e48ee"
    }
]