[
    {
        "accuracy": 0.6859,
        "batch": 32,
        "dropout": 0.30716165466476353,
        "dropout_aux": 0.022401724050103655,
        "duration": 4210807895576,
        "lr": 0.002708431725677493,
        "momentum": 0.7451172315263975,
        "transform": "echo_299",
        "uid": "da55c9dde5978775fd5bd2a25ba30f7c"
    },
    {
        "accuracy": 0.5946,
        "batch": 8,
        "dropout": 0.21137587715507572,
        "dropout_aux": 0.665698253605643,
        "duration": 6704816700618,
        "lr": 0.00020146979749790083,
        "momentum": 0.5945674321156895,
        "transform": "norm_512",
        "uid": "0b17a74996dcaec972c2acb7e731740a"
    },
    {
        "accuracy": 0.5615,
        "batch": 256,
        "dropout": 0.10036334519927825,
        "dropout_aux": 0.6819100157553444,
        "duration": 3945807771760,
        "lr": 0.41864516530705437,
        "momentum": 0.22555828956367052,
        "transform": "norm_128",
        "uid": "0569b7c4fc159e4f4739937c652abad8"
    },
    {
        "accuracy": 0.495,
        "batch": 64,
        "dropout": 0.22591427404168957,
        "dropout_aux": 0.31304269005136365,
        "duration": 6825400954008,
        "lr": 0.0009916078349911858,
        "momentum": 0.5396747660202702,
        "transform": "echo_512",
        "uid": "53e2f70be2ec21d263bd008f22b18899"
    },
    {
        "accuracy": 0.4657,
        "batch": 64,
        "dropout": 0.38538956069165037,
        "dropout_aux": 0.1886260759382451,
        "duration": 782135105953,
        "lr": 0.0007310231207789283,
        "momentum": 0.8505926724162879,
        "transform": "norm_32",
        "uid": "d945d521099f5fd1b69597577cec08b0"
    },
    {
        "accuracy": 0.4297,
        "batch": 128,
        "dropout": 0.03816544669382743,
        "dropout_aux": 0.10388728392035029,
        "duration": 11660010460871,
        "lr": 0.0008919382391027481,
        "momentum": 0.058039566643328655,
        "transform": "norm_256_flip",
        "uid": "0e4973cb746d6b6d4d18550b0f88c7a3"
    },
    {
        "accuracy": 0.3655,
        "batch": 128,
        "dropout": 0.2166419448642819,
        "dropout_aux": 0.5977264115757257,
        "duration": 133437750050,
        "lr": 0.17805538693506348,
        "momentum": 0.12992534184297533,
        "transform": "echo_32",
        "uid": "9ccb2d738847d8855fefbd6211b47413"
    },
    {
        "accuracy": 0.3022,
        "batch": 32,
        "dropout": 0.04060991817578463,
        "dropout_aux": 0.8078477901498654,
        "duration": 1156644628630,
        "lr": 1.830575341356704e-05,
        "momentum": 0.8115903867165457,
        "transform": "norm",
        "uid": "c5fc4032a5dcb6cc995436466abdee42"
    },
    {
        "accuracy": 0.1287,
        "batch": 64,
        "dropout": 0.23160265461401636,
        "dropout_aux": 0.20910130866387444,
        "duration": 548609278392,
        "lr": 4.822460315991222e-05,
        "momentum": 0.04858820755350146,
        "transform": "norm_128_flip",
        "uid": "ee16125c3ed6243336ff559f3c2efe0c"
    }
]