[
    {
        "accuracy": 0.810540872771973,
        "batch": 64,
        "duration": 1502723654064,
        "lr": 0.00033783484214681254,
        "momentum": 0.8616420818065211,
        "transform": "norm_32",
        "uid": "13540502f4b2152d992f3932d4c135b7"
    },
    {
        "accuracy": 0.7860709895513215,
        "batch": 4,
        "duration": 4152160416419,
        "lr": 0.00038778083309837675,
        "momentum": 0.3710012912145261,
        "transform": "echo",
        "uid": "2a35f4e5220a71df9812768ef98a2a28"
    }
]