[
    {
        "accuracy": 0.8367778119237861,
        "batch": 64,
        "duration": 2394495224221,
        "lr": 0.00033783484214681254,
        "momentum": 0.8616420818065211,
        "transform": "norm_32",
        "uid": "3dd7a90e1633ddc141d7fe0cc34ae247"
    },
    {
        "accuracy": 0.8337814996926859,
        "batch": 256,
        "duration": 1398611987494,
        "lr": 0.18256815322838185,
        "momentum": 0.8047353361332708,
        "transform": "echo",
        "uid": "b77146c93d4e89d42eb120b68d8f7ddf"
    },
    {
        "accuracy": 0.821181622618316,
        "batch": 4,
        "duration": 6846641179001,
        "lr": 0.00038778083309837675,
        "momentum": 0.3710012912145261,
        "transform": "echo",
        "uid": "17b2c3c6c799c473ac8348aad8a815ee"
    }
]