[
    {
        "accuracy": 0.9941,
        "batch": 32,
        "duration": 599932063185,
        "lr": 0.4854716233699751,
        "momentum": 0.44703421266765764,
        "transform": "echo",
        "uid": "b38590fc0111f958c1da3c3a6aaeca0f"
    },
    {
        "accuracy": 0.982,
        "batch": 2048,
        "duration": 1440020057110,
        "lr": 0.16862984411186646,
        "momentum": 0.863711129019964,
        "transform": "norm_flip",
        "uid": "369de11986bacd3b9097f50239d90895"
    },
    {
        "accuracy": 0.9378,
        "batch": 32,
        "duration": 2713417920854,
        "lr": 0.052797113039853405,
        "momentum": 0.9359045525935769,
        "transform": "echo_128_flip",
        "uid": "62be0c9f47646f582c1af13cf24f3993"
    }
]