[
    {
        "accuracy": 0.1089,
        "batch": 4,
        "dropout": 0.00763321223985014,
        "duration": 115937011796,
        "lr": 0.013847391135481562,
        "momentum": 0.5772551527800337,
        "transform": "echo",
        "uid": "8d96d56071bd9eb7207f9c95c64a56df"
    },
    {
        "accuracy": 0.0928,
        "batch": 4,
        "dropout": 0.4711759930742664,
        "duration": 113347630775,
        "lr": 0.06250915772975026,
        "momentum": 0.4493496696220527,
        "transform": "norm",
        "uid": "19cddd219697ed100d2a062fe171bb8b"
    },
    {
        "accuracy": 0.0462,
        "batch": 64,
        "dropout": 0.4737172002229794,
        "duration": 102723605602,
        "lr": 0.019446201599684656,
        "momentum": 0.25794684297044823,
        "transform": "norm_299",
        "uid": "8c289423bb14fb53ecfbea3513791a0b"
    }
]