[
    {
        "accuracy": 0.9190227412415488,
        "batch": 16,
        "duration": 693847924220,
        "lr": 0.12755242555030835,
        "momentum": 0.8195864010924716,
        "transform": "echo_flip",
        "uid": "bf03f7aa8d8df648c89751826e0c4570"
    },
    {
        "accuracy": 0.9162569145666871,
        "batch": 256,
        "duration": 68883009672,
        "lr": 0.4308002453420352,
        "momentum": 0.9069849568851219,
        "transform": "norm_32_flip",
        "uid": "30f2ef2bbe678abb2120f6cb0a1c56cb"
    },
    {
        "accuracy": 0.9139904732636754,
        "batch": 64,
        "duration": 362020247045,
        "lr": 0.071193883704645,
        "momentum": 0.7248942556974869,
        "transform": "echo_32_flip",
        "uid": "db039f57f9f8f3951a9a6a9df0cf69ab"
    },
    {
        "accuracy": 0.8748079287031346,
        "batch": 256,
        "duration": 40167281818,
        "lr": 0.00823901377207448,
        "momentum": 0.18004268472941853,
        "transform": "echo_flip",
        "uid": "83900d5510cc58181d0cbbe361ef0528"
    },
    {
        "accuracy": 0.5783650891210818,
        "batch": 128,
        "duration": 2123599879350,
        "lr": 0.004019193157888591,
        "momentum": 0.5656221034034714,
        "transform": "echo_299_flip",
        "uid": "27dab044d7d9a10da0a6f5c2bf374d32"
    },
    {
        "accuracy": 0.21112476951444376,
        "batch": 512,
        "duration": 496567636549,
        "lr": 6.739643098884398e-05,
        "momentum": 0.6827145099834621,
        "transform": "echo_64",
        "uid": "34d27b7fe657f8a3d77e1efb011964ad"
    },
    {
        "accuracy": 0.2103180700676091,
        "batch": 64,
        "duration": 114298231956,
        "lr": 2.6497146658349304e-05,
        "momentum": 0.4614183530381524,
        "transform": "norm_64_flip",
        "uid": "6a60ddecf3b25bb29080db579c436f7e"
    }
]