[
    {
        "accuracy": 0.9249769514443762,
        "batch": 256,
        "duration": 94733321128,
        "lr": 0.4308002453420352,
        "momentum": 0.9069849568851219,
        "transform": "norm_32_flip",
        "uid": "55cce2071f9ddcce41f6ae38ab5f3834"
    },
    {
        "accuracy": 0.8730792870313461,
        "batch": 256,
        "duration": 55163793843,
        "lr": 0.00823901377207448,
        "momentum": 0.18004268472941853,
        "transform": "echo_flip",
        "uid": "343a0f073a6adf52bb27137abe5ed18b"
    },
    {
        "accuracy": 0.6657959434542102,
        "batch": 128,
        "duration": 2919724963483,
        "lr": 0.004019193157888591,
        "momentum": 0.5656221034034714,
        "transform": "echo_299_flip",
        "uid": "33563acb14966b868bfc40af0d36cb4b"
    },
    {
        "accuracy": 0.22748924400737552,
        "batch": 64,
        "duration": 156988177668,
        "lr": 2.6497146658349304e-05,
        "momentum": 0.4614183530381524,
        "transform": "norm_64_flip",
        "uid": "7de5799b9e420a3be83dbc76e6414132"
    },
    {
        "accuracy": 0.2259142593730793,
        "batch": 512,
        "duration": 685402471817,
        "lr": 6.739643098884398e-05,
        "momentum": 0.6827145099834621,
        "transform": "echo_64",
        "uid": "8164e7923667bba1f329ef43b7604517"
    }
]