[
    {
        "accuracy": 0.6264,
        "batch": 64,
        "dropout": 0.4451624223665932,
        "duration": 216305908536,
        "lr": 0.8129003593156321,
        "momentum": 0.6259832193269793,
        "transform": "echo_64_flip",
        "uid": "605ff02e7ea553ce981e52ac1df9f865"
    },
    {
        "accuracy": 0.4871,
        "batch": 2,
        "dropout": 0.25060355280977886,
        "duration": 1222309095687,
        "lr": 0.4999054259753829,
        "momentum": 0.14202527544742938,
        "transform": "echo_flip",
        "uid": "908700d971489265192a97b90893019f"
    },
    {
        "accuracy": 0.4433,
        "batch": 512,
        "dropout": 0.12176302307510617,
        "duration": 225817300806,
        "lr": 0.04183355297255443,
        "momentum": 0.5068653905532057,
        "transform": "echo_64",
        "uid": "752de0f8cfb683b7f501fc2ff84d0f18"
    },
    {
        "accuracy": 0.363,
        "batch": 64,
        "dropout": 0.06395339219727258,
        "duration": 879141540572,
        "lr": 0.0019713236448578803,
        "momentum": 0.7768698876924858,
        "transform": "norm_128",
        "uid": "a7afd396905c3f9d8051530bf03ad2b2"
    },
    {
        "accuracy": 0.0311,
        "batch": 1,
        "dropout": 0.19277641622508845,
        "duration": 2467519825861,
        "lr": 0.003965092498653094,
        "momentum": 0.602574206328673,
        "transform": "echo_128_flip",
        "uid": "be0f8acba8d348a5702d157be3d30b98"
    }
]