[
    {
        "accuracy": 0.1187,
        "batch": 4,
        "duration": 3985466806553,
        "lr": 0.010503084556958427,
        "momentum": 0.30968070309187024,
        "transform": "echo_256",
        "uid": "7ff92228f8b84478c8ff185391710787"
    },
    {
        "accuracy": 0.0858,
        "batch": 8,
        "duration": 1794174927590,
        "lr": 0.4609881969003342,
        "momentum": 0.5298195720216783,
        "transform": "echo_32",
        "uid": "0723a415e9af646f08f25f02ef7c5f66"
    },
    {
        "accuracy": 0.0156,
        "batch": 2,
        "duration": 3858751459523,
        "lr": 1.5060839333412007e-05,
        "momentum": 0.5425324167412605,
        "transform": "norm",
        "uid": "44a426229e33ce4180d0619c0759c92e"
    }
]