[
    {
        "accuracy": 0.5401,
        "batch": 16,
        "dropout": 0.23875408609558002,
        "duration": 6124394673835,
        "lr": 0.0003615994384883547,
        "momentum": 0.060520707085912506,
        "transform": "norm_512",
        "uid": "3abde87a84788d1509fd3a644131813c"
    },
    {
        "accuracy": 0.5204,
        "batch": 4,
        "dropout": 0.4942808835379797,
        "duration": 2992998483781,
        "lr": 0.0007058736376078056,
        "momentum": 0.8361231033345634,
        "transform": "echo_256_flip",
        "uid": "5b5ef0638eb49548e1501a0352b363e0"
    },
    {
        "accuracy": 0.4519,
        "batch": 256,
        "dropout": 0.05169395159977658,
        "duration": 2588428059018,
        "lr": 0.0003428672992871887,
        "momentum": 0.5124718326891385,
        "transform": "norm_299",
        "uid": "4594a002da771b50001e5103e49af2bb"
    },
    {
        "accuracy": 0.2043,
        "batch": 512,
        "dropout": 0.20420229987213945,
        "duration": 335921168267,
        "lr": 2.0908464723466144e-05,
        "momentum": 0.4838341005974319,
        "transform": "norm_128",
        "uid": "414775db7f7ae91b0aff10a055347ed0"
    },
    {
        "accuracy": 0.1866,
        "batch": 256,
        "dropout": 0.10406371601938874,
        "duration": 1671664708629,
        "lr": 1.366237833320949e-05,
        "momentum": 0.43352890505926756,
        "transform": "norm_128_flip",
        "uid": "4e037ef10b6dda630127934275419ce4"
    }
]