[
    {
        "accuracy": 0.39862476951444376,
        "batch": 4,
        "duration": 2200929505464,
        "lr": 0.14890708509485812,
        "momentum": 0.1648012291594061,
        "transform": "norm_32_flip",
        "uid": "c4b4a7b5a340895816ea381f67c59071"
    },
    {
        "accuracy": 0.3468423478795329,
        "batch": 128,
        "duration": 878366100680,
        "lr": 0.2378876518808912,
        "momentum": 0.5778191130428089,
        "transform": "complex_32",
        "uid": "f4f512e0362d921ffae395c4352e7e40"
    }
]