[
    {
        "accuracy": 0.26513521819299324,
        "batch": 128,
        "duration": 197383098417,
        "lr": 0.2378876518808912,
        "momentum": 0.5778191130428089,
        "transform": "complex_32",
        "uid": "fd2be712b7a68917eae349bbdbfa3c55"
    },
    {
        "accuracy": 0.21112476951444376,
        "batch": 4,
        "duration": 516230258758,
        "lr": 0.14890708509485812,
        "momentum": 0.1648012291594061,
        "transform": "norm_32_flip",
        "uid": "b94b46b7200261b2b716cdb383cf9ead"
    }
]