[
    {
        "accuracy": 0.3919022741241549,
        "batch": 1024,
        "duration": 2095858731701,
        "lr": 0.0058163360613793175,
        "momentum": 0.7217212059395806,
        "transform": "echo_64",
        "uid": "68499c1d596e725ff6b469d8f7268641"
    },
    {
        "accuracy": 0.30593116164720346,
        "batch": 2048,
        "duration": 1754685706231,
        "lr": 0.003997780053801539,
        "momentum": 0.5595739070713145,
        "transform": "echo_32_flip",
        "uid": "4f587935bbf6244ade7b4fdaece031fb"
    }
]