[
    {
        "accuracy": 0.3189,
        "batch": 16,
        "duration": 6416886452711,
        "lr": 0.0049134941270017225,
        "momentum": 0.4718387645077645,
        "transform": "complex_512_flip",
        "uid": "8d757e900fbe8edb28e84e7858577b30"
    },
    {
        "accuracy": 0.2531,
        "batch": 32,
        "duration": 303585196706,
        "lr": 0.0001506953589852698,
        "momentum": 0.8435440906009839,
        "transform": "complex_128",
        "uid": "afce11e6f050893994cb6de7f2d31269"
    },
    {
        "accuracy": 0.246,
        "batch": 16,
        "duration": 7057053122430,
        "lr": 0.05861397903111362,
        "momentum": 0.40801513557757374,
        "transform": "complex_299_flip",
        "uid": "ce6734d858bd98d1f33b87a3e4413f97"
    },
    {
        "accuracy": 0.239,
        "batch": 4096,
        "duration": 90636838973,
        "lr": 0.13223329090535238,
        "momentum": 0.9512588179443766,
        "transform": "complex_64",
        "uid": "b98286771db09151a12453dc99e96764"
    },
    {
        "accuracy": 0.1961,
        "batch": 64,
        "duration": 320388387058,
        "lr": 0.000934715857513235,
        "momentum": 0.16724661319333234,
        "transform": "complex",
        "uid": "f8418630c0a468d897156ffa6a2f453d"
    }
]