[
    {
        "accuracy": 0.91279963122311,
        "batch": 32,
        "duration": 1146836526726,
        "lr": 0.3092231145538556,
        "momentum": 0.4057217387801265,
        "transform": "norm_32_flip",
        "uid": "25c80635c69d24487a1a2ccbaaabb228"
    },
    {
        "accuracy": 0.2403580208973571,
        "batch": 512,
        "duration": 972963687393,
        "lr": 0.00012646055378160085,
        "momentum": 0.5105457217757837,
        "transform": "echo_64",
        "uid": "8df9028614759d352f61bfa5452d5806"
    }
]